unique_id/__init__.py
unique_id/generator.py
unique_id_package-0.2.0.dist-info/LICENSE
unique_id_package-0.2.0.dist-info/METADATA
unique_id_package-0.2.0.dist-info/WHEEL
unique_id_package-0.2.0.dist-info/top_level.txt
unique_id_package-0.2.0.dist-info/RECORD
