Metadata-Version: 2.1
Name: unique-id-package
Version: 0.2.0
Summary: A package to generate unique IDs
Home-page: https://github.com/your-github/unique_id_package
Author: Abhishek Kumar
Author-email: your-email@example.com
License: UNKNOWN
Platform: UNKNOWN
Classifier: Programming Language :: Python :: 3
Classifier: License :: OSI Approved :: MIT License
Classifier: Operating System :: OS Independent
Requires-Python: >=3.6
License-File: LICENSE
